pyviscous/__init__.py
pyviscous/plot.py
pyviscous/pyviscous.py
pyviscous-2.2.2.dist-info/licenses/LICENSE
pyviscous-2.2.2.dist-info/METADATA
pyviscous-2.2.2.dist-info/WHEEL
pyviscous-2.2.2.dist-info/top_level.txt
pyviscous-2.2.2.dist-info/RECORD
