Metadata-Version: 2.4
Name: pyviscous
Version: 2.2.2
Summary: Python codes to implement the VISCOUS global sensitivity analysis framework
Home-page: https://github.com/CH-Earth/pyviscous
Author: Hongli Liu
Author-email: Hongli Liu <hongliliu68@gmail.com>
License-Expression: GPL-3.0-only
Project-URL: Homepage, https://github.com/CH-Earth/pyviscous
Requires-Python: >=3.6
License-File: LICENSE
Requires-Dist: wheel>=0.36
Requires-Dist: copulae
Dynamic: author
Dynamic: home-page
Dynamic: license-file
Dynamic: requires-python
